kommonlib/__init__.py
kommonlib/py.typed
kommonlib/registry/__init__.py
kommonlib/registry/common.py
kommonlib/registry/namespace.py
kommonlib-0.1.3.dist-info/METADATA
kommonlib-0.1.3.dist-info/WHEEL
kommonlib-0.1.3.dist-info/licenses/LICENSE
kommonlib-0.1.3.dist-info/RECORD
